README.md
setup.py
qcc_wallet.egg-info/PKG-INFO
qcc_wallet.egg-info/SOURCES.txt
qcc_wallet.egg-info/dependency_links.txt
qcc_wallet.egg-info/requires.txt
qcc_wallet.egg-info/top_level.txt
qccwallet/__init__.py
qccwallet/extra_passport.py
qccwallet/db/__init__.py
qccwallet/db/mongo.py
qccwallet/http_handler/__init__.py
qccwallet/http_handler/contract_handler.py
qccwallet/http_handler/entrance_handler.py
qccwallet/http_handler/wallet_handler.py
qccwallet/routes/__init__.py
qccwallet/routes/wallet.py
qccwallet/routes/wallet_ws.py
qccwallet/service/__init__.py
qccwallet/service/ctrl_contract.py
qccwallet/service/ctrl_wallet.py
qccwallet/service/async_wrap/__init__.py
qccwallet/service/async_wrap/ctrl_contract.py
qccwallet/service/external/__init__.py
qccwallet/service/external/ethereum.py
qccwallet/service/internal/__init__.py
qccwallet/service/internal/ethereum.py
qccwallet/service/task/__init__.py
qccwallet/service/task/tx_engine.py
qccwallet/utils/__init__.py
qccwallet/utils/coinnum.py
qccwallet/utils/secret.py
qccwallet/ws_handler/__init__.py
qccwallet/ws_handler/dispatcher.py