Metadata-Version: 1.2
Name: qcc-wallet
Version: 0.2.7
Summary: All like QCC wallet manage business can from qcc-wallet. Web-mother include member manage, organization manage, and catalog manage. Especially qcc-wallet support authorization management.
Home-page: https://gitee.com/qcc100/qcc-wallet.git
Author: Yang Chunbo
Author-email: ycb@microto.com
Maintainer: Yang Chunbo
Maintainer-email: ycb@microto.com
License: MIT License
Platform: all
Classifier: Development Status :: 4 - Beta
Classifier: Operating System :: OS Independent
Classifier: Intended Audience :: Developers
Classifier: License :: OSI Approved :: MIT License
Classifier: Programming Language :: Python
Classifier: Programming Language :: Python :: Implementation
Classifier: Programming Language :: Python :: 3.6
Classifier: Topic :: Software Development :: Libraries
